colorschemes/VERSION.txt
colorschemes/__init__.py
colorschemes/colorschemes.py
colorschemes-1.1.1.dist-info/LICENSE
colorschemes-1.1.1.dist-info/METADATA
colorschemes-1.1.1.dist-info/WHEEL
colorschemes-1.1.1.dist-info/top_level.txt
colorschemes-1.1.1.dist-info/RECORD
