Metadata-Version: 2.1
Name: colorschemes
Version: 1.1.1
Summary: colorschemes: A package for aesthetically pleasing and colorblindness-friendly color schemes
Author: Ethan Dintzner
Classifier: License :: OSI Approved :: MIT License
Classifier: Development Status :: 5 - Production/Stable
Classifier: Programming Language :: Python :: 3
Classifier: Programming Language :: Python :: 3.9
Classifier: Programming Language :: Python :: 3.10
Classifier: Programming Language :: Python :: 3.11
Classifier: Programming Language :: Python :: 3.12
License-File: LICENSE
Requires-Dist: numpy (>=2.0.0)
Requires-Dist: matplotlib (>=3.0.0)
